spice_solver/__init__.py
spice_solver/dummy.py
spice_solver-0.0.2.dist-info/METADATA
spice_solver-0.0.2.dist-info/WHEEL
spice_solver-0.0.2.dist-info/licenses/LICENSE
spice_solver-0.0.2.dist-info/RECORD
