Metadata-Version: 2.4
Name: spice-solver
Version: 0.0.2
Summary: Name reservation for future developments.
Project-URL: Source, https://github.com/bertpl/spice-solver
Project-URL: ChangeLog, https://github.com/bertpl/spice-solver/blob/main/CHANGELOG.md
Project-URL: Issues, https://github.com/bertpl/spice-solver/issues
Project-URL: Roadmap, https://github.com/bertpl/spice-solver/milestones
Author-email: Bert Pluymers <bert.pluymers@gmail.com>
License-File: LICENSE
Requires-Python: >=3.11
Requires-Dist: numpy>=1.20
